plaid2qif/__init__.py
plaid2qif/plaid2qif.py
plaid2qif/transaction_writer.py
plaid2qif/util.py
plaid2qif-1.4.0.dist-info/entry_points.txt
plaid2qif-1.4.0.dist-info/LICENSE.md
plaid2qif-1.4.0.dist-info/WHEEL
plaid2qif-1.4.0.dist-info/METADATA
plaid2qif-1.4.0.dist-info/RECORD
