Metadata-Version: 2.1
Name: plaid2qif
Version: 1.4.0
Summary: Download financial transactions from Plaid as QIF files.
Home-page: https://github.com/ebridges/plaid2qif
License: MIT
Author: Edward Q. Bridges
Author-email: github@eqbridges.com
Requires-Python: >=3.9,<4.0
Classifier: Development Status :: 5 - Production/Stable
Classifier: Intended Audience :: End Users/Desktop
Classifier: Intended Audience :: Financial and Insurance Industry
Classifier: License :: OSI Approved :: MIT License
Classifier: Programming Language :: Python :: 3
Classifier: Programming Language :: Python :: 3.10
Classifier: Programming Language :: Python :: 3.9
Classifier: Topic :: Home Automation
Classifier: Topic :: Office/Business :: Financial
Classifier: Topic :: Office/Business :: Financial :: Accounting
Classifier: Topic :: Utilities
Requires-Dist: docopt (>=0.6.2,<0.7.0)
Requires-Dist: plaid-python (>=9.4.0,<10.0.0)
Requires-Dist: python-dateutil (>=2.8.1,<3.0.0)
Requires-Dist: python-dotenv (>=0.20.0,<0.21.0)
Project-URL: Repository, https://github.com/ebridges/plaid2qif
